Metadata-Version: 2.4
Name: PySide6-Fluent-Widgets_yh
Version: 1.8.1
Summary: A fluent design widgets library based on PySide6
Home-page: https://qfluentwidgets.com
Author: zhiyiYo
Author-email: shokokawaii@outlook.com
License: GPLv3
Project-URL: Documentation, https://qfluentwidgets.com/
Project-URL: Source Code, https://github.com/zhiyiYo/PyQt-Fluent-Widgets/tree/PySide6
Project-URL: Bug Tracker, https://github.com/zhiyiYo/PyQt-Fluent-Widgets/issues
Keywords: pyside6 fluent widgets
Classifier: Programming Language :: Python :: 3
Classifier: License :: OSI Approved :: GNU General Public License v3 (GPLv3)
Classifier: Operating System :: OS Independent
License-File: LICENSE
Requires-Dist: PySide6>=6.4.2
Requires-Dist: PySideSix-Frameless-Window>=0.4.0
Requires-Dist: darkdetect
Provides-Extra: full
Requires-Dist: scipy; extra == "full"
Requires-Dist: pillow; extra == "full"
Requires-Dist: colorthief; extra == "full"
Dynamic: author
Dynamic: author-email
Dynamic: classifier
Dynamic: description
Dynamic: description-content-type
Dynamic: home-page
Dynamic: keywords
Dynamic: license
Dynamic: license-file
Dynamic: project-url
Dynamic: provides-extra
Dynamic: requires-dist
Dynamic: summary
